{"scores":{"Fall '13":{"course_score":{"overall":"3.20","workload":"2.20","difficulty":"4.20","recommendation":"3.00","enrollment":"5","response rate":"80.00","QCourseOverall":{"number":"E-PSCI 136","course_id":"11344","cat_num":"33894","1s":"0","2s":"2","3s":"0","4s":"1","5s":"1"},"QDifficulty":{"number":"E-PSCI 136","course_id":"11344","cat_num":"33894","1s":"0","2s":"0","3s":"1","4s":"1","5s":"2"},"QWorkload":{"number":"E-PSCI 136","course_id":"11344","cat_num":"33894","1s":"0","2s":"3","3s":"1","4s":"0","5s":"0"}},"instructor_scores":[{"number":"E-PSCI 136","cat_num":"33894","course_id":"11344","year":"2013","term":"1","id":"aec5b9c72386bd389d051719115e1432","first":" Carl","last":"Wunsch","InstructorOverall":"3.20","EffectiveLecturesorPresentations":"2.80","AccessibleOutsideClass":"4.20","GeneratesEnthusiasm":"3.20","FacilitatesDiscussionEncouragesParticipation":"2.70","GivesUsefulFeedback":"3.00","ReturnsAssignmentsinTimelyFashion":"3.20"}]}},"comments":[],"mostRecentQ":{"overall":"3.20","workload":"2.20","difficulty":"4.20","recommendation":"3.00","enrollment":"5","response rate":"80.00","QCourseOverall":{"number":"E-PSCI 136","course_id":"11344","cat_num":"33894","1s":"0","2s":"2","3s":"0","4s":"1","5s":"1"},"QDifficulty":{"number":"E-PSCI 136","course_id":"11344","cat_num":"33894","1s":"0","2s":"0","3s":"1","4s":"1","5s":"2"},"QWorkload":{"number":"E-PSCI 136","course_id":"11344","cat_num":"33894","1s":"0","2s":"3","3s":"1","4s":"0","5s":"0"}},"success":true}